mesonet_alerts/__init__.py
mesonet_alerts/config.py
mesonet_alerts/config_repo.py
mesonet_alerts/dropcheck.py
mesonet_alerts/emailer.py
mesonet_alerts/retry.py
mesonet_alerts/store.py
mesonet_alerts/templates.py
mesonet_alerts-0.2.5.dist-info/METADATA
mesonet_alerts-0.2.5.dist-info/WHEEL
mesonet_alerts-0.2.5.dist-info/RECORD
