Metadata-Version: 2.4
Name: mesonet-alerts
Version: 0.2.5
Summary: Shared email alerting, retries, and volume-drop checks for Mesonet workers
Project-URL: Homepage, https://github.com/dwd94/mesonet-alerts
Author-email: Dawood Siddiq <dawood.siddiq@codingcops.com>
License: Proprietary
Keywords: alerts,dynamodb,email,jinja2,retry
Classifier: Operating System :: POSIX :: Linux
Classifier: Programming Language :: Python :: 3
Classifier: Programming Language :: Python :: 3.11
Classifier: Typing :: Typed
Requires-Python: >=3.11
Requires-Dist: boto3>=1.33
Requires-Dist: jinja2>=3.1
Requires-Dist: python-dotenv>=1.0.0
Provides-Extra: dev
Requires-Dist: mypy>=1.7.0; extra == 'dev'
Requires-Dist: pytest-cov>=4.1.0; extra == 'dev'
Requires-Dist: pytest-mock>=3.11.0; extra == 'dev'
Requires-Dist: pytest>=7.4.3; extra == 'dev'
Requires-Dist: python-dotenv>=1.0.1; extra == 'dev'
Requires-Dist: ruff>=0.1.6; extra == 'dev'
